num_tini4/__init__.py
num_tini4/num.py
num_tini4/primes.py
num_tini4-0.2.0a1.dist-info/METADATA
num_tini4-0.2.0a1.dist-info/WHEEL
num_tini4-0.2.0a1.dist-info/licenses/LICENSE
num_tini4-0.2.0a1.dist-info/RECORD
