Metadata-Version: 2.1
Name: num_tini4
Version: 0.2.0a1
Summary: Python precise number type.
Project-URL: Documentation, https://github.com/Tini4/Num/wiki
Project-URL: Source Code, https://github.com/Tini4/Num
Project-URL: Bug Tracker, https://github.com/Tini4/Num/issues
Author-email: Tini4 <tilen.jurican@gmail.com>
License: Creative Commons Attribution-NonCommercial-NoDerivatives 4.0 International Public License
License-File: LICENSE
Classifier: Development Status :: 1 - Planning
Classifier: License :: Other/Proprietary License
Classifier: Operating System :: OS Independent
Classifier: Programming Language :: Python :: 3.10
Classifier: Programming Language :: Python :: 3.11
Classifier: Topic :: Scientific/Engineering :: Mathematics
Requires-Python: >=3.10
